flag/__init__.py
flag/admin.py
flag/apps.py
flag/exceptions.py
flag/managers.py
flag/mixins.py
flag/models.py
flag/signals.py
flag/urls.py
flag/utils.py
flag/views.py
flag/api/__init__.py
flag/api/serializers.py
flag/api/urls.py
flag/api/views.py
flag/conf/__init__.py
flag/conf/defaults.py
flag/migrations/0001_initial.py
flag/migrations/__init__.py
flag/static/flag/css/flag.css
flag/static/flag/js/flag.js
flag/templates/flag/flag_form.html
flag/templates/flag/flag_icon.html
flag/templatetags/__init__.py
flag/templatetags/flag_tags.py
django_flag_app-2.0.0.dist-info/METADATA
django_flag_app-2.0.0.dist-info/WHEEL
django_flag_app-2.0.0.dist-info/licenses/LICENSE
django_flag_app-2.0.0.dist-info/RECORD
