Metadata-Version: 2.4
Name: django-flag-app
Version: 2.0.0
Summary: A pluggable django application that adds the ability for users to flag(or report) your models
Project-URL: Documentation, https://django-flag-app.readthedocs.io
Project-URL: Source Code, https://github.com/abhiabhi94/django-flag-app
Project-URL: Homepage, https://github.com/abhiabhi94/django-flag-app
Author: Abhyudai
License-Expression: MIT
License-File: LICENSE
Keywords: django,flag,moderate,report
Classifier: Environment :: Web Environment
Classifier: Framework :: Django
Classifier: Framework :: Django :: 4.2
Classifier: Framework :: Django :: 5.0
Classifier: Framework :: Django :: 5.1
Classifier: Framework :: Django :: 5.2
Classifier: Intended Audience :: Developers
Classifier: License :: OSI Approved :: MIT License
Classifier: Operating System :: OS Independent
Classifier: Programming Language :: Python
Classifier: Programming Language :: Python :: 3.10
Classifier: Programming Language :: Python :: 3.11
Classifier: Programming Language :: Python :: 3.12
Classifier: Programming Language :: Python :: 3.13
Classifier: Topic :: Internet :: WWW/HTTP
Classifier: Topic :: Internet :: WWW/HTTP :: Dynamic Content
Requires-Python: >=3.10
Requires-Dist: django
